outagedetector/__init__.py
outagedetector/__main__.py
outagedetector/cron_scheduling.py
outagedetector/initial_config.py
outagedetector/outage_detector.py
outagedetector/pushnotification.py
outagedetector/send_mail.py
Outage_Detector-1.1.2.dist-info/LICENSE
Outage_Detector-1.1.2.dist-info/METADATA
Outage_Detector-1.1.2.dist-info/WHEEL
Outage_Detector-1.1.2.dist-info/entry_points.txt
Outage_Detector-1.1.2.dist-info/top_level.txt
Outage_Detector-1.1.2.dist-info/RECORD
