Metadata-Version: 2.1
Name: Outage-Detector
Version: 1.1.2
Summary: A module helping you find out when internet and power outages happen.
Home-page: https://github.com/fabytm/Outage-Detector
Author: Butean Fabian
Author-email: buteanfabian@gmail.com
License: MIT
Platform: UNKNOWN
Requires-Dist: python-crontab (==2.4.2)
Requires-Dist: keyring (==20.0.1)
Requires-Dist: keyrings.alt (==3.2.0)
Requires-Dist: certifi (==2019.9.11)
Requires-Dist: chardet (==3.0.4)
Requires-Dist: idna (==2.8)
Requires-Dist: pushbullet.py (==0.11.0)
Requires-Dist: python-magic (==0.4.15)
Requires-Dist: requests (==2.22.0)
Requires-Dist: six (==1.13.0)
Requires-Dist: urllib3 (==1.25.6)
Requires-Dist: websocket-client (==0.56.0)
